{
    "title": "Persuasion, Inc.: The Invisible Forces Shaping Our Economy and Culture",
    "words_per_chapter": 5000,
    "chapters": [
      {
        "title": "Introduction: The Unseen Hand",
        "subtopics": [
          "The invisible influence of data and algorithms",
          "A personal realization of social media’s manipulation",
          "From Bernays to Big Data: a historical lineage of persuasion",
          "The illusion of free will in the digital age"
        ],
        "key_points": [
          "Data has become the primary mechanism of control in modern society.",
          "Our choices are shaped by invisible forces of media, marketing, and algorithms.",
          "The future of autonomy depends on recognizing and resisting digital manipulation."
        ],
        "connections": ["Sets up Chapter 1: The Architecture of Influence"]
      },
      {
        "title": "Chapter 1: The Architecture of Influence",
        "subtopics": [
          "Defining persuasion versus manipulation",
          "History of influence systems: from myth to media",
          "How belief systems are designed and maintained"
        ],
        "key_points": [
          "Persuasion has evolved from storytelling and religion into systemic behavioral control.",
          "Media has always been the architecture through which beliefs are constructed.",
          "Influence is not random—it’s engineered through systems that reinforce compliance."
        ],
        "connections": ["Builds on Introduction", "Leads to Chapter 2: Invisible Currents"]
      },
      {
        "title": "Chapter 2: Invisible Currents",
        "subtopics": [
          "Ideology as environment",
          "Narrative as infrastructure",
          "The illusion of neutrality in media and institutions"
        ],
        "key_points": [
          "Ideologies are not opinions—they’re the water we swim in.",
          "Narratives structure perception by deciding what stories are visible or hidden.",
          "Neutrality is a myth; every system of communication carries bias."
        ],
        "connections": ["Builds on Chapter 1", "Leads to Chapter 3: You Are the Product"]
      },
      {
        "title": "Chapter 3: You Are the Product. And the Output.",
        "subtopics": [
          "The attention economy and commercialized identity",
          "Social mirroring and performance culture",
          "Surveillance capitalism and data as capital"
        ],
        "key_points": [
          "Humans are both consumers and commodities within the attention economy.",
          "Our identities are shaped through feedback loops of validation and algorithmic visibility.",
          "Data is the new raw material for economic and psychological manipulation."
        ],
        "connections": ["Concludes Part I: Foundations of Persuasion", "Sets up Part II: Systems of Control"]
      },
      {
        "title": "Chapter 4: Marketing as Cultural Infrastructure",
        "subtopics": [
          "Brands as belief systems",
          "Marketing as modern myth-making",
          "Emotional engineering and identity packaging"
        ],
        "key_points": [
          "Marketing has evolved from selling products to constructing entire worldviews.",
          "Brands function as modern religions—symbols through which people find meaning.",
          "Emotions are engineered to bind consumers to corporate ideologies."
        ],
        "connections": ["Builds on Chapter 3", "Leads to Chapter 5: Media and Consent"]
      },
      {
        "title": "Chapter 5: Media, Messaging, and the Manufacturing of Consent",
        "subtopics": [
          "Entertainment as influence pipeline",
          "News, memes, and manufactured memory",
          "Everything is an ad, even this"
        ],
        "key_points": [
          "Mass media and entertainment are persuasive infrastructures disguised as leisure.",
          "The repetition of symbols and narratives constructs shared memories and beliefs.",
          "In a commercial ecosystem, every message functions as an advertisement for something."
        ],
        "connections": ["Builds on Chapter 4", "Leads to Chapter 6: Designing the Illusion of Free Will"]
      },
      {
        "title": "Chapter 6: Designing the Illusion of Free Will",
        "subtopics": [
          "Choice architecture and behavioral economics",
          "UX design and persuasive technology",
          "Algorithmic determinism and AI persuasion"
        ],
        "key_points": [
          "Modern design subtly narrows our choices while preserving the illusion of freedom.",
          "AI-driven personalization systems continuously optimize persuasion loops.",
          "Free will is constrained not by force but by interface."
        ],
        "connections": ["Concludes Part II: Systems of Control", "Sets up Part III: The Technology of Belief"]
      },
      {
        "title": "Chapter 7: The Algorithmic Mind",
        "subtopics": [
          "How AI learns to persuade and predict",
          "Personalized influence and behavioral modeling",
          "The rise of synthetic personality and synthetic truth"
        ],
        "key_points": [
          "AI doesn’t just reflect human bias—it learns to exploit it.",
          "Behavioral prediction transforms persuasion into preemptive control.",
          "Synthetic personas blur the boundary between authentic and artificial influence."
        ],
        "connections": ["Builds on Chapter 6", "Leads to Chapter 8: Commercial Realities, Virtual Beliefs"]
      },
      {
        "title": "Chapter 8: Commercial Realities, Virtual Beliefs",
        "subtopics": [
          "Influencers, echo chambers, and parasocial control",
          "False gods, true feelings: emotional loyalty to illusions",
          "The currency of conviction in digital economies"
        ],
        "key_points": [
          "Influencer culture transforms belief into commodity and parasocial relationships into power.",
          "Digital identities are structured around loyalty, not truth.",
          "Conviction itself has become monetizable capital."
        ],
        "connections": ["Concludes Part III: The Technology of Belief", "Sets up Part IV: Consequences of the Unseen"]
      },
      {
        "title": "Chapter 9: Democracy, Capitalism, and the Theater of Control",
        "subtopics": [
          "Who benefits from your beliefs?",
          "Corporate-state synergy and ideological engineering",
          "Monetized morality and performative politics"
        ],
        "key_points": [
          "Economic and political systems use persuasion as governance.",
          "The merging of corporate and state interests has turned belief into policy.",
          "Public morality is often a performance orchestrated by systems of influence."
        ],
        "connections": ["Builds on Chapter 8", "Leads to Chapter 10: Psychological Decay"]
      },
      {
        "title": "Chapter 10: Psychological Decay in a World of Influence",
        "subtopics": [
          "Cognitive overload and decision fatigue",
          "Learned helplessness and dopamine loops",
          "Crisis addiction and the erosion of agency"
        ],
        "key_points": [
          "Constant persuasion induces cognitive exhaustion and emotional dependency.",
          "Attention economies exploit human neurochemistry to sustain engagement.",
          "The result is a collective psychological decay that benefits systems of control."
        ],
        "connections": ["Concludes Part IV: Consequences of the Unseen", "Sets up Part V: Awakening the Observer"]
      },
      {
        "title": "Chapter 11: Systemic Self-Awareness",
        "subtopics": [
          "Learning to see the layers of influence",
          "Mindfulness in the age of manipulation",
          "Reclaiming narrative sovereignty"
        ],
        "key_points": [
          "Awareness is the antidote to systemic manipulation.",
          "Mindfulness practices can be reframed as tools of cultural deprogramming.",
          "Narrative sovereignty begins with identifying whose story you are living."
        ],
        "connections": ["Builds on Chapter 10", "Leads to Chapter 12: Designing Ethically"]
      },
      {
        "title": "Chapter 12: Designing Ethically – New Frameworks for Influence",
        "subtopics": [
          "Conscious marketing and ethical persuasion",
          "Transparency and responsible design in AI and education",
          "Rebuilding trust, truth, and transparency"
        ],
        "key_points": [
          "Ethical design means using persuasion to empower rather than exploit.",
          "Transparency and consent must become cornerstones of digital communication.",
          "Education is both the battlefield and the solution for reclaiming human agency."
        ],
        "connections": ["Concludes Part V", "Leads to Epilogue"]
      },
      {
        "title": "Epilogue: The Next Belief System",
        "subtopics": [
          "What comes after persuasion?",
          "The future of human autonomy and consciousness",
          "A call to conscious participation in shaping the next paradigm"
        ],
        "key_points": [
          "Persuasion will evolve—but so must our awareness.",
          "The next belief system will be built on transparency, not manipulation.",
          "To know we are being shaped is the first step toward shaping ourselves."
        ],
        "connections": ["Closes the book, echoes the Introduction"]
      }
    ]
  }
  
